<?xml version="1.0" encoding="UTF-8"?>
<game>
	<id>2073148</id>
	<board>
		<nameBoard>Temple</nameBoard>
		<sizeBoard>30</sizeBoard>
		<players>
			<player>
				<name>lu</name>
				<position>11</position>
				<coins>23</coins>
			</player>
			<player>
				<name>do</name>
				<position>9</position>
				<coins>25</coins>
			</player>
			<player>
				<name>ivan</name>
				<position>8</position>
				<coins>17</coins>
			</player>
		</players>
		<effects>
			<effect>
				<effectName>Begin</effectName>
				<message>It's the beginning, everyone start with 5 coins!</message>
				<value>19</value>
				<cost>0</cost>
			</effect>
			<effect>
				<effectName>Bonus</effectName>
				<message>You gain 6 coins!</message>
				<value>6</value>
				<cost>-6</cost>
			</effect>
			<effect>
				<effectName>Bonus</effectName>
				<message>You gain 6 coins!</message>
				<value>6</value>
				<cost>-6</cost>
			</effect>
			<effect>
				<effectName>Loose</effectName>
				<message>You loose 2 coins...</message>
				<value>-2</value>
				<cost>-2</cost>
			</effect>
			<effect>
				<effectName>Empty</effectName>
				<message>Nothing happened.</message>
				<value>0</value>
				<cost>-1</cost>
			</effect>
			<effect>
				<effectName>Empty</effectName>
				<message>Nothing happened.</message>
				<value>0</value>
				<cost>-1</cost>
			</effect>
			<effect>
				<effectName>Bonus</effectName>
				<message>You gain 6 coins!</message>
				<value>6</value>
				<cost>-6</cost>
			</effect>
			<effect>
				<effectName>Loose</effectName>
				<message>You loose 2 coins...</message>
				<value>-2</value>
				<cost>-2</cost>
			</effect>
			<effect>
				<effectName>Empty</effectName>
				<message>Nothing happened.</message>
				<value>0</value>
				<cost>-1</cost>
			</effect>
			<effect>
				<effectName>Bonus</effectName>
				<message>You gain 6 coins!</message>
				<value>6</value>
				<cost>-6</cost>
			</effect>
			<effect>
				<effectName>Loose</effectName>
				<message>You loose 2 coins...</message>
				<value>-2</value>
				<cost>-2</cost>
			</effect>
			<effect>
				<effectName>Bonus</effectName>
				<message>You gain 6 coins!</message>
				<value>6</value>
				<cost>-6</cost>
			</effect>
			<effect>
				<effectName>Bonus</effectName>
				<message>You gain 6 coins!</message>
				<value>6</value>
				<cost>-6</cost>
			</effect>
			<effect>
				<effectName>Empty</effectName>
				<message>Nothing happened.</message>
				<value>0</value>
				<cost>-1</cost>
			</effect>
			<effect>
				<effectName>Loose</effectName>
				<message>You loose 2 coins...</message>
				<value>-2</value>
				<cost>-2</cost>
			</effect>
			<effect>
				<effectName>Pen4a</effectName>
				<message>What the *family friendly game*, everyone loose 1 coin!</message>
				<value>-1</value>
				<cost>-1</cost>
			</effect>
			<effect>
				<effectName>Pen4a</effectName>
				<message>What the *family friendly game*, everyone loose 1 coin!</message>
				<value>-1</value>
				<cost>-1</cost>
			</effect>
			<effect>
				<effectName>Pen4a</effectName>
				<message>What the *family friendly game*, everyone loose 1 coin!</message>
				<value>-1</value>
				<cost>-1</cost>
			</effect>
			<effect>
				<effectName>Loose</effectName>
				<message>You loose 2 coins...</message>
				<value>-2</value>
				<cost>-2</cost>
			</effect>
			<effect>
				<effectName>Loose</effectName>
				<message>You loose 2 coins...</message>
				<value>-2</value>
				<cost>-2</cost>
			</effect>
			<effect>
				<effectName>Loose</effectName>
				<message>You loose 2 coins...</message>
				<value>-2</value>
				<cost>-2</cost>
			</effect>
			<effect>
				<effectName>Pen4a</effectName>
				<message>What the *family friendly game*, everyone loose 1 coin!</message>
				<value>-1</value>
				<cost>-1</cost>
			</effect>
			<effect>
				<effectName>Pen4a</effectName>
				<message>What the *family friendly game*, everyone loose 1 coin!</message>
				<value>-1</value>
				<cost>-1</cost>
			</effect>
			<effect>
				<effectName>Empty</effectName>
				<message>Nothing happened.</message>
				<value>0</value>
				<cost>-1</cost>
			</effect>
			<effect>
				<effectName>Loose</effectName>
				<message>You loose 2 coins...</message>
				<value>-2</value>
				<cost>-2</cost>
			</effect>
			<effect>
				<effectName>Pen4a</effectName>
				<message>What the *family friendly game*, everyone loose 1 coin!</message>
				<value>-1</value>
				<cost>-1</cost>
			</effect>
			<effect>
				<effectName>Loose</effectName>
				<message>You loose 2 coins...</message>
				<value>-2</value>
				<cost>-2</cost>
			</effect>
			<effect>
				<effectName>Pen4a</effectName>
				<message>What the *family friendly game*, everyone loose 1 coin!</message>
				<value>-1</value>
				<cost>-1</cost>
			</effect>
			<effect>
				<effectName>Loose</effectName>
				<message>You loose 2 coins...</message>
				<value>-2</value>
				<cost>-2</cost>
			</effect>
			<effect>
				<effectName>Pen4a</effectName>
				<message>What the *family friendly game*, everyone loose 1 coin!</message>
				<value>-1</value>
				<cost>-1</cost>
			</effect>
		</effects>
	</board>
</game>
